README.rst
setup.py
serverless_db_sdk/__init__.py
serverless_db_sdk/database.py
serverless_db_sdk/err.py
serverless_db_sdk/test.py
serverless_db_sdk.egg-info/PKG-INFO
serverless_db_sdk.egg-info/SOURCES.txt
serverless_db_sdk.egg-info/dependency_links.txt
serverless_db_sdk.egg-info/requires.txt
serverless_db_sdk.egg-info/top_level.txt