Metadata-Version: 1.0
Name: serverless-db-sdk
Version: 0.0.1
Summary: serverless_db_sdk
Home-page: http://qcloud.com
Author: rangeli
Author-email: 709738544@qq.com
License: MIT Licence
Keywords: pip,serverless,serverless db,serverless_db_sdk
Platform: any
